lcls/.lc.rules.yaml
lcls/__init__.py
lcls-1.0.4.dist-info/METADATA
lcls-1.0.4.dist-info/WHEEL
lcls-1.0.4.dist-info/entry_points.txt
lcls-1.0.4.dist-info/top_level.txt
lcls-1.0.4.dist-info/RECORD
