Metadata-Version: 2.1
Name: lcls
Version: 1.0.4
Summary: lc is ls but with colors and icons.
Home-page: https://github.com/pouya-eghbali/lc
Author: Pouya Eghbali
Author-email: pouya.eghbali@yandex.com
Requires-Dist: sty
Requires-Dist: ruamel.yaml
